racedata/__init__.py
racedata-0.0.dist-info/METADATA
racedata-0.0.dist-info/WHEEL
racedata-0.0.dist-info/DESCRIPTION.rst
racedata-0.0.dist-info/RECORD
racedata-0.0.dist-info/top_level.txt
racedata-0.0.dist-info/metadata.json
test/__init__.py
