Metadata-Version: 2.0
Name: racedata
Version: 0.0
Summary: Race Data 0.0
Home-page: https://github.com/SenorPez/project-cars-race-data
Author: Senor Pez
Author-email: contact_at_github@example.org
License: MIT
Keywords: gaming racing video data streaming
Platform: UNKNOWN
Classifier: Development Status :: 4 - Beta
Classifier: Intended Audience :: End Users/Desktop
Classifier: License :: OSI Approved :: MIT License
Classifier: Programming Language :: Python :: 3.3
Classifier: Programming Language :: Python :: 3.4
Classifier: Programming Language :: Python :: 3.5
Classifier: Programming Language :: Python :: 3.6
Classifier: Programming Language :: Python :: 3 :: Only
Requires-Dist: tqdm
